gvxrPython3/JSON2gVXRDataReader.py
gvxrPython3/__init__.py
gvxrPython3/computeLBuffer.py
gvxrPython3/gVXRDataReader.py
gvxrPython3/gvxr2json.py
gvxrPython3/gvxr2radiograph.py
gvxrPython3/json2gvxr.py
gvxrPython3/test.py
gvxrPython3/test_exception.py
gvxrPython3/test_offscreen.py
gvxrPython3/utils.py
gvxrPython3/_gvxrPython3/_temp_gvxrPython3.so
gvxrPython3/_gvxrPython3/temp_gvxrPython3.py
gvxrPython3/_gvxrPython3/welsh-dragon-small.stl
gvxr-2.0.10.dist-info/LICENSE
gvxr-2.0.10.dist-info/METADATA
gvxr-2.0.10.dist-info/WHEEL
gvxr-2.0.10.dist-info/top_level.txt
gvxr-2.0.10.dist-info/RECORD
gvxr.libs/libXinerama-b7a62e01.so.1.0.0
gvxr.libs/libsatlas-7e2f78d2.so.3.10
gvxr.libs/libgfortran-91cc3cb1.so.3.0.0
gvxr.libs/libGLdispatch-dcc1ca97.so.0.0.0
gvxr.libs/libgomp-a34b3233.so.1.0.0
gvxr.libs/libffi-af4ed708.so.6.0.1
gvxr.libs/libquadmath-96973f99.so.0.0.0
gvxr.libs/libXxf86vm-3971cbbb.so.1.0.0
gvxr.libs/libXcursor-1a09904e.so.1.0.2
gvxr.libs/libgbm-c8ef9fa6.so.1.0.0
gvxr.libs/libz-4e3ca1c7.so.1.2.7
gvxr.libs/libwayland-server-6781a35c.so.0.1.0
gvxr.libs/libXfixes-d274cb03.so.3.1.0
gvxr.libs/libXi-e28fba09.so.6.1.0
gvxr.libs/libEGL-29b68110.so.1.1.0
gvxr.libs/libdrm-827b956f.so.2.4.0
gvxr.libs/libgsl-cb3064f9.so.0.16.0
gvxr.libs/libgslcblas-9055a056.so.0.0.0
gvxr.libs/libXrandr-1b5fae8f.so.2.2.0
