Metadata-Version: 2.2
Name: gvxr
Version: 2.0.10
Summary: gVirtualXray (gVXR) Bindings to simulate realist X-ray attenuation images in microseconds from triangle meshes.
Home-page: https://gvirtualxray.sourceforge.io/
Author: Prof Franck P. Vidal
License: Copyright (c) 2019, Dr Franck P. Vidal (franck.p.vidal@fpvidal.net), http://www.fpvidal.net/
Project-URL: Homepage, https://gvirtualxray.sourceforge.io/
Project-URL: Bug Tracker, https://sourceforge.net/p/gvirtualxray/tickets/
Classifier: Operating System :: MacOS
Classifier: Operating System :: Microsoft :: Windows
Classifier: Operating System :: POSIX :: Linux
Classifier: Environment :: GPU
Classifier: Development Status :: 4 - Beta
Classifier: Environment :: MacOS X
Classifier: Environment :: Win32 (MS Windows)
Classifier: Environment :: X11 Applications
Classifier: Intended Audience :: Science/Research
Classifier: License :: OSI Approved :: BSD License
Classifier: Programming Language :: C++
Classifier: Programming Language :: C#
Classifier: Programming Language :: Java
Classifier: Programming Language :: Python :: 3
Classifier: Programming Language :: R
Classifier: Programming Language :: Ruby
Classifier: Programming Language :: Tcl
Classifier: Topic :: Games/Entertainment :: Simulation
Classifier: Topic :: Scientific/Engineering :: Physics
Classifier: Topic :: Software Development :: Libraries
Requires-Python: >=3.6
License-File: LICENSE
Requires-Dist: xpecgen
Requires-Dist: spekpy
Requires-Dist: scikit-image
Requires-Dist: numpy
Requires-Dist: matplotlib
Requires-Dist: pillow
Dynamic: home-page
Dynamic: requires-python
